<?xml version="1.0" encoding="UTF-8" ?><document><annotations itct="CAAQwOYBIhMI4s7gpYnv3wIVRvcDCh1vOwghKPgdMgJpdkj20Nad1abO3Wo">
<annotation id="annotation_1609960065" type="text" style="popup" log_data="ei=_3E9XKLTG8buD-_2oIgC&amp;link=http%3A%2F%2Fwww.youtube.com%2Fwatch%3Fv%3Dars5NVO1qHY%23t%3D2m4s&amp;a-v=ars5NVO1qHY&amp;a-id=annotation_1609960065&amp;xble=1&amp;l-class=1&amp;a-type=1" itct="CAEQs-UBGP___________wEiEwjizuClie_fAhVG9wMKHW87CCEo-B0yAml2SPbQ1p3Vps7dag">
  
  <segment>
    <movingRegion type="rect">
      <rectRegion x="80.03200" y="39.43700" w="19.85700" h="21.00000" t="0:00.000"/>
      <rectRegion x="80.03200" y="39.43700" w="19.85700" h="21.00000" t="0:16.600"/>
    </movingRegion>
  </segment>
  <appearance bgAlpha="0.25" bgColor="0" fgColor="16777215" textSize="3.911599999999999" effects="">
    
  </appearance>
  
  <action type="openUrl" trigger="click">
    <url target="current" value="https://www.youtube.com/watch?annotation_id=annotation_1609960065&amp;ei=_3E9XKLTG8buD-_2oIgC&amp;feature=iv&amp;src_vid=ars5NVO1qHY&amp;v=ars5NVO1qHY#t=2m4s" link_class="1"/>
  </action>

</annotation>
<annotation id="annotation_1760263137" type="text" style="popup" log_data="ei=_3E9XKLTG8buD-_2oIgC&amp;link=http%3A%2F%2Fwww.youtube.com%2Fwatch%3Fv%3Dars5NVO1qHY%23t%3D2m46s&amp;a-v=ars5NVO1qHY&amp;a-id=annotation_1760263137&amp;xble=1&amp;l-class=1&amp;a-type=1" itct="CAIQs-UBGP___________wEiEwjizuClie_fAhVG9wMKHW87CCEo-B0yAml2SPbQ1p3Vps7dag">
  
  <segment>
    <movingRegion type="rect">
      <rectRegion x="29.95200" y="0.00000" w="20.17400" h="19.87300" t="0:00.000"/>
      <rectRegion x="29.95200" y="0.00000" w="20.17400" h="19.87300" t="0:16.600"/>
    </movingRegion>
  </segment>
  <appearance bgAlpha="0.25" bgColor="0" fgColor="16777215" textSize="3.911599999999999" effects="">
    
  </appearance>
  
  <action type="openUrl" trigger="click">
    <url target="current" value="https://www.youtube.com/watch?annotation_id=annotation_1760263137&amp;ei=_3E9XKLTG8buD-_2oIgC&amp;feature=iv&amp;src_vid=ars5NVO1qHY&amp;v=ars5NVO1qHY#t=2m46s" link_class="1"/>
  </action>

</annotation>
<annotation id="annotation_1913378287" type="text" style="popup" log_data="ei=_3E9XKLTG8buD-_2oIgC&amp;link=http%3A%2F%2Fwww.youtube.com%2Fwatch%3Fv%3Dars5NVO1qHY%23t%3D1m54s&amp;a-v=ars5NVO1qHY&amp;a-id=annotation_1913378287&amp;xble=1&amp;l-class=1&amp;a-type=1" itct="CAMQs-UBGP___________wEiEwjizuClie_fAhVG9wMKHW87CCEo-B0yAml2SPbQ1p3Vps7dag">
  
  <segment>
    <movingRegion type="rect">
      <rectRegion x="59.74600" y="39.43700" w="20.65000" h="19.02800" t="0:00.000"/>
      <rectRegion x="59.74600" y="39.43700" w="20.65000" h="19.02800" t="0:16.600"/>
    </movingRegion>
  </segment>
  <appearance bgAlpha="0.25" bgColor="0" fgColor="16777215" textSize="3.911599999999999" effects="">
    
  </appearance>
  
  <action type="openUrl" trigger="click">
    <url target="current" value="https://www.youtube.com/watch?annotation_id=annotation_1913378287&amp;ei=_3E9XKLTG8buD-_2oIgC&amp;feature=iv&amp;src_vid=ars5NVO1qHY&amp;v=ars5NVO1qHY#t=1m54s" link_class="1"/>
  </action>

</annotation>
<annotation id="annotation_2097423813" type="text" style="popup" log_data="ei=_3E9XKLTG8buD-_2oIgC&amp;link=http%3A%2F%2Fwww.youtube.com%2Fwatch%3Fv%3Dars5NVO1qHY%23t%3D21s&amp;a-v=ars5NVO1qHY&amp;a-id=annotation_2097423813&amp;xble=1&amp;l-class=1&amp;a-type=1" itct="CAQQs-UBGP___________wEiEwjizuClie_fAhVG9wMKHW87CCEo-B0yAml2SPbQ1p3Vps7dag">
  
  <segment>
    <movingRegion type="rect">
      <rectRegion x="59.74600" y="79.71800" w="20.17400" h="20.28200" t="0:00.000"/>
      <rectRegion x="59.74600" y="79.71800" w="20.17400" h="20.28200" t="0:16.600"/>
    </movingRegion>
  </segment>
  <appearance bgAlpha="0.25" bgColor="0" fgColor="16777215" textSize="3.911599999999999" effects="">
    
  </appearance>
  
  <action type="openUrl" trigger="click">
    <url target="current" value="https://www.youtube.com/watch?annotation_id=annotation_2097423813&amp;ei=_3E9XKLTG8buD-_2oIgC&amp;feature=iv&amp;src_vid=ars5NVO1qHY&amp;v=ars5NVO1qHY#t=21s" link_class="1"/>
  </action>

</annotation>
<annotation id="annotation_2362475077" type="text" style="popup" log_data="ei=_3E9XKLTG8buD-_2oIgC&amp;link=http%3A%2F%2Fwww.youtube.com%2Fwatch%3Fv%3Dars5NVO1qHY%23t%3D1m35s&amp;a-v=ars5NVO1qHY&amp;a-id=annotation_2362475077&amp;xble=1&amp;l-class=1&amp;a-type=1" itct="CAUQs-UBGP___________wEiEwjizuClie_fAhVG9wMKHW87CCEo-B0yAml2SPbQ1p3Vps7dag">
  
  <segment>
    <movingRegion type="rect">
      <rectRegion x="19.81000" y="39.43700" w="20.48300" h="20.15500" t="0:00.000"/>
      <rectRegion x="19.81000" y="39.43700" w="20.48300" h="20.15500" t="0:16.600"/>
    </movingRegion>
  </segment>
  <appearance bgAlpha="0.25" bgColor="0" fgColor="16777215" textSize="3.911599999999999" effects="">
    
  </appearance>
  
  <action type="openUrl" trigger="click">
    <url target="current" value="https://www.youtube.com/watch?annotation_id=annotation_2362475077&amp;ei=_3E9XKLTG8buD-_2oIgC&amp;feature=iv&amp;src_vid=ars5NVO1qHY&amp;v=ars5NVO1qHY#t=1m35s" link_class="1"/>
  </action>

</annotation>
<annotation id="annotation_2720071679" type="text" style="popup" log_data="ei=_3E9XKLTG8buD-_2oIgC&amp;link=http%3A%2F%2Fwww.youtube.com%2Fwatch%3Fv%3Dars5NVO1qHY%23t%3D1m45s&amp;a-v=ars5NVO1qHY&amp;a-id=annotation_2720071679&amp;xble=1&amp;l-class=1&amp;a-type=1" itct="CAYQs-UBGP___________wEiEwjizuClie_fAhVG9wMKHW87CCEo-B0yAml2SPbQ1p3Vps7dag">
  
  <segment>
    <movingRegion type="rect">
      <rectRegion x="40.09500" y="39.43700" w="20.17400" h="20.71800" t="0:00.000"/>
      <rectRegion x="40.09500" y="39.43700" w="20.17400" h="20.71800" t="0:16.600"/>
    </movingRegion>
  </segment>
  <appearance bgAlpha="0.25" bgColor="0" fgColor="16777215" textSize="3.911599999999999" effects="">
    
  </appearance>
  
  <action type="openUrl" trigger="click">
    <url target="current" value="https://www.youtube.com/watch?annotation_id=annotation_2720071679&amp;ei=_3E9XKLTG8buD-_2oIgC&amp;feature=iv&amp;src_vid=ars5NVO1qHY&amp;v=ars5NVO1qHY#t=1m45s" link_class="1"/>
  </action>

</annotation>
<annotation id="annotation_3016721719" type="text" style="popup" log_data="ei=_3E9XKLTG8buD-_2oIgC&amp;link=http%3A%2F%2Fwww.youtube.com%2Fwatch%3Fv%3Dars5NVO1qHY%23t%3D1m19s&amp;a-v=ars5NVO1qHY&amp;a-id=annotation_3016721719&amp;xble=1&amp;l-class=1&amp;a-type=1" itct="CAcQs-UBGP___________wEiEwjizuClie_fAhVG9wMKHW87CCEo-B0yAml2SPbQ1p3Vps7dag">
  
  <segment>
    <movingRegion type="rect">
      <rectRegion x="69.88900" y="59.71800" w="20.17400" h="20.15500" t="0:00.000"/>
      <rectRegion x="69.88900" y="59.71800" w="20.17400" h="20.15500" t="0:16.600"/>
    </movingRegion>
  </segment>
  <appearance bgAlpha="0.25" bgColor="0" fgColor="16777215" textSize="3.911599999999999" effects="">
    
  </appearance>
  
  <action type="openUrl" trigger="click">
    <url target="current" value="https://www.youtube.com/watch?annotation_id=annotation_3016721719&amp;ei=_3E9XKLTG8buD-_2oIgC&amp;feature=iv&amp;src_vid=ars5NVO1qHY&amp;v=ars5NVO1qHY#t=1m19s" link_class="1"/>
  </action>

</annotation>
<annotation id="annotation_3035561801" type="text" style="popup" log_data="ei=_3E9XKLTG8buD-_2oIgC&amp;link=http%3A%2F%2Fwww.youtube.com%2Fwatch%3Fv%3Dars5NVO1qHY%23t%3D1m27s&amp;a-v=ars5NVO1qHY&amp;a-id=annotation_3035561801&amp;xble=1&amp;l-class=1&amp;a-type=1" itct="CAgQs-UBGP___________wEiEwjizuClie_fAhVG9wMKHW87CCEo-B0yAml2SPbQ1p3Vps7dag">
  
  <segment>
    <movingRegion type="rect">
      <rectRegion x="0.00000" y="39.43700" w="20.16600" h="20.43700" t="0:00.000"/>
      <rectRegion x="0.00000" y="39.43700" w="20.16600" h="20.43700" t="0:16.600"/>
    </movingRegion>
  </segment>
  <appearance bgAlpha="0.25" bgColor="0" fgColor="16777215" textSize="3.911599999999999" effects="">
    
  </appearance>
  
  <action type="openUrl" trigger="click">
    <url target="current" value="https://www.youtube.com/watch?annotation_id=annotation_3035561801&amp;ei=_3E9XKLTG8buD-_2oIgC&amp;feature=iv&amp;src_vid=ars5NVO1qHY&amp;v=ars5NVO1qHY#t=1m27s" link_class="1"/>
  </action>

</annotation>
<annotation id="annotation_3245813493" type="text" style="popup" log_data="ei=_3E9XKLTG8buD-_2oIgC&amp;link=http%3A%2F%2Fwww.youtube.com%2Fwatch%3Fv%3Dars5NVO1qHY%23t%3D57s&amp;a-v=ars5NVO1qHY&amp;a-id=annotation_3245813493&amp;xble=1&amp;l-class=1&amp;a-type=1" itct="CAkQs-UBGP___________wEiEwjizuClie_fAhVG9wMKHW87CCEo-B0yAml2SPbQ1p3Vps7dag">
  
  <segment>
    <movingRegion type="rect">
      <rectRegion x="29.95200" y="59.71800" w="20.32500" h="20.71800" t="0:00.000"/>
      <rectRegion x="29.95200" y="59.71800" w="20.32500" h="20.71800" t="0:16.600"/>
    </movingRegion>
  </segment>
  <appearance bgAlpha="0.25" bgColor="0" fgColor="16777215" textSize="3.911599999999999" effects="">
    
  </appearance>
  
  <action type="openUrl" trigger="click">
    <url target="current" value="https://www.youtube.com/watch?annotation_id=annotation_3245813493&amp;ei=_3E9XKLTG8buD-_2oIgC&amp;feature=iv&amp;src_vid=ars5NVO1qHY&amp;v=ars5NVO1qHY#t=57s" link_class="1"/>
  </action>

</annotation>
<annotation id="annotation_3335270241" type="text" style="popup" log_data="ei=_3E9XKLTG8buD-_2oIgC&amp;link=http%3A%2F%2Fwww.youtube.com%2Fwatch%3Fv%3Dars5NVO1qHY%23t%3D46s&amp;a-v=ars5NVO1qHY&amp;a-id=annotation_3335270241&amp;xble=1&amp;l-class=1&amp;a-type=1" itct="CAoQs-UBGP___________wEiEwjizuClie_fAhVG9wMKHW87CCEo-B0yAml2SPbQ1p3Vps7dag">
  
  <segment>
    <movingRegion type="rect">
      <rectRegion x="9.82600" y="59.15500" w="20.17400" h="20.43700" t="0:00.000"/>
      <rectRegion x="9.82600" y="59.15500" w="20.17400" h="20.43700" t="0:16.600"/>
    </movingRegion>
  </segment>
  <appearance bgAlpha="0.25" bgColor="0" fgColor="16777215" textSize="3.911599999999999" effects="">
    
  </appearance>
  
  <action type="openUrl" trigger="click">
    <url target="current" value="https://www.youtube.com/watch?annotation_id=annotation_3335270241&amp;ei=_3E9XKLTG8buD-_2oIgC&amp;feature=iv&amp;src_vid=ars5NVO1qHY&amp;v=ars5NVO1qHY#t=46s" link_class="1"/>
  </action>

</annotation>
<annotation id="annotation_3800654247" type="text" style="popup" log_data="ei=_3E9XKLTG8buD-_2oIgC&amp;link=http%3A%2F%2Fwww.youtube.com%2Fwatch%3Fv%3Dars5NVO1qHY%23t%3D2m26s&amp;a-v=ars5NVO1qHY&amp;a-id=annotation_3800654247&amp;xble=1&amp;l-class=1&amp;a-type=1" itct="">
  
  <segment>
    <movingRegion type="rect">
      <rectRegion x="39.93700" y="19.71800" w="20.17400" h="20.43700" t="0:00.000"/>
      <rectRegion x="39.93700" y="19.71800" w="20.17400" h="20.43700" t="0:16.600"/>
    </movingRegion>
  </segment>
  <appearance bgAlpha="0.25" bgColor="0" fgColor="16777215" textSize="3.911599999999999" effects="">
    
  </appearance>
  
  <action type="openUrl" trigger="click">
    <url target="current" value="https://www.youtube.com/watch?annotation_id=annotation_3800654247&amp;ei=_3E9XKLTG8buD-_2oIgC&amp;feature=iv&amp;src_vid=ars5NVO1qHY&amp;v=ars5NVO1qHY#t=2m26s" link_class="1"/>
  </action>

</annotation>
<annotation id="annotation_3871850087" type="text" style="popup" log_data="ei=_3E9XKLTG8buD-_2oIgC&amp;link=http%3A%2F%2Fwww.youtube.com%2Fwatch%3Fv%3Dars5NVO1qHY%23t%3D16s&amp;a-v=ars5NVO1qHY&amp;a-id=annotation_3871850087&amp;xble=1&amp;l-class=1&amp;a-type=1" itct="">
  
  <segment>
    <movingRegion type="rect">
      <rectRegion x="19.81000" y="79.43700" w="20.32500" h="20.56300" t="0:00.000"/>
      <rectRegion x="19.81000" y="79.43700" w="20.32500" h="20.56300" t="0:16.586"/>
    </movingRegion>
  </segment>
  <appearance bgAlpha="0.25" bgColor="0" fgColor="16777215" textSize="3.911599999999999" effects="">
    
  </appearance>
  
  <action type="openUrl" trigger="click">
    <url target="current" value="https://www.youtube.com/watch?annotation_id=annotation_3871850087&amp;ei=_3E9XKLTG8buD-_2oIgC&amp;feature=iv&amp;src_vid=ars5NVO1qHY&amp;v=ars5NVO1qHY#t=16s" link_class="1"/>
  </action>

</annotation>
<annotation id="annotation_3993705477" type="text" style="popup" log_data="ei=_3E9XKLTG8buD-_2oIgC&amp;link=http%3A%2F%2Fwww.youtube.com%2Fwatch%3Fv%3Dars5NVO1qHY%23t%3D2m15s&amp;a-v=ars5NVO1qHY&amp;a-id=annotation_3993705477&amp;xble=1&amp;l-class=1&amp;a-type=1" itct="">
  
  <segment>
    <movingRegion type="rect">
      <rectRegion x="19.81000" y="19.43700" w="20.32500" h="20.71800" t="0:00.000"/>
      <rectRegion x="19.81000" y="19.43700" w="20.32500" h="20.71800" t="0:16.600"/>
    </movingRegion>
  </segment>
  <appearance bgAlpha="0.25" bgColor="0" fgColor="16777215" textSize="3.911599999999999" effects="">
    
  </appearance>
  
  <action type="openUrl" trigger="click">
    <url target="current" value="https://www.youtube.com/watch?annotation_id=annotation_3993705477&amp;ei=_3E9XKLTG8buD-_2oIgC&amp;feature=iv&amp;src_vid=ars5NVO1qHY&amp;v=ars5NVO1qHY#t=2m15s" link_class="1"/>
  </action>

</annotation>
<annotation id="annotation_528245185" type="text" style="popup" log_data="ei=_3E9XKLTG8buD-_2oIgC&amp;link=http%3A%2F%2Fwww.youtube.com%2Fwatch%3Fv%3Dars5NVO1qHY%23t%3D25s&amp;a-v=ars5NVO1qHY&amp;a-id=annotation_528245185&amp;xble=1&amp;l-class=1&amp;a-type=1" itct="">
  
  <segment>
    <movingRegion type="rect">
      <rectRegion x="39.62000" y="79.71800" w="20.49100" h="20.28200" t="0:00.000"/>
      <rectRegion x="39.62000" y="79.71800" w="20.49100" h="20.28200" t="0:16.600"/>
    </movingRegion>
  </segment>
  <appearance bgAlpha="0.25" bgColor="0" fgColor="16777215" textSize="3.911599999999999" effects="">
    
  </appearance>
  
  <action type="openUrl" trigger="click">
    <url target="current" value="https://www.youtube.com/watch?annotation_id=annotation_528245185&amp;ei=_3E9XKLTG8buD-_2oIgC&amp;feature=iv&amp;src_vid=ars5NVO1qHY&amp;v=ars5NVO1qHY#t=25s" link_class="1"/>
  </action>

</annotation>
<annotation id="annotation_835416971" type="text" style="popup" log_data="ei=_3E9XKLTG8buD-_2oIgC&amp;link=http%3A%2F%2Fwww.youtube.com%2Fwatch%3Fv%3Dars5NVO1qHY&amp;a-v=ars5NVO1qHY&amp;a-id=annotation_835416971&amp;xble=1&amp;l-class=1&amp;a-type=1" itct="">
  <TEXT>Back to beginning!</TEXT>
  <segment>
    <movingRegion type="rect">
      <rectRegion x="0.00000" y="0.00000" w="21.11700" h="7.19700" t="0:16.600"/>
      <rectRegion x="0.00000" y="0.00000" w="21.11700" h="7.19700" t="3:06.084"/>
    </movingRegion>
  </segment>
  <appearance bgAlpha="0.25" bgColor="0" fgColor="16777215" textSize="3.911599999999999" effects="">
    
  </appearance>
  
  <action type="openUrl" trigger="click">
    <url target="current" value="https://www.youtube.com/watch?annotation_id=annotation_835416971&amp;ei=_3E9XKLTG8buD-_2oIgC&amp;feature=iv&amp;src_vid=ars5NVO1qHY&amp;v=ars5NVO1qHY" link_class="1"/>
  </action>

</annotation>
<annotation id="annotation_920769259" type="text" style="popup" log_data="ei=_3E9XKLTG8buD-_2oIgC&amp;link=http%3A%2F%2Fwww.youtube.com%2Fwatch%3Fv%3Dars5NVO1qHY%23t%3D1m9s&amp;a-v=ars5NVO1qHY&amp;a-id=annotation_920769259&amp;xble=1&amp;l-class=1&amp;a-type=1" itct="">
  
  <segment>
    <movingRegion type="rect">
      <rectRegion x="49.76200" y="59.71800" w="20.33300" h="20.43700" t="0:00.000"/>
      <rectRegion x="49.76200" y="59.71800" w="20.33300" h="20.43700" t="0:16.600"/>
    </movingRegion>
  </segment>
  <appearance bgAlpha="0.25" bgColor="0" fgColor="16777215" textSize="3.911599999999999" effects="">
    
  </appearance>
  
  <action type="openUrl" trigger="click">
    <url target="current" value="https://www.youtube.com/watch?annotation_id=annotation_920769259&amp;ei=_3E9XKLTG8buD-_2oIgC&amp;feature=iv&amp;src_vid=ars5NVO1qHY&amp;v=ars5NVO1qHY#t=1m9s" link_class="1"/>
  </action>

</annotation>
<annotation id="annotation_942031935" type="text" style="popup" log_data="ei=_3E9XKLTG8buD-_2oIgC&amp;link=http%3A%2F%2Fwww.youtube.com%2Fwatch%3Fv%3Dars5NVO1qHY%23t%3D2m37s&amp;a-v=ars5NVO1qHY&amp;a-id=annotation_942031935&amp;xble=1&amp;l-class=1&amp;a-type=1" itct="">
  
  <segment>
    <movingRegion type="rect">
      <rectRegion x="59.90500" y="19.71800" w="20.33300" h="19.87300" t="0:00.000"/>
      <rectRegion x="59.90500" y="19.71800" w="20.33300" h="19.87300" t="0:16.600"/>
    </movingRegion>
  </segment>
  <appearance bgAlpha="0.25" bgColor="0" fgColor="16777215" textSize="3.911599999999999" effects="">
    
  </appearance>
  
  <action type="openUrl" trigger="click">
    <url target="current" value="https://www.youtube.com/watch?annotation_id=annotation_942031935&amp;ei=_3E9XKLTG8buD-_2oIgC&amp;feature=iv&amp;src_vid=ars5NVO1qHY&amp;v=ars5NVO1qHY#t=2m37s" link_class="1"/>
  </action>

</annotation>
<annotation id="annotation_970789757" type="text" style="popup" log_data="ei=_3E9XKLTG8buD-_2oIgC&amp;link=http%3A%2F%2Fwww.youtube.com%2Fwatch%3Fv%3Dars5NVO1qHY%23t%3D2m56s&amp;a-v=ars5NVO1qHY&amp;a-id=annotation_970789757&amp;xble=1&amp;l-class=1&amp;a-type=1" itct="">
  
  <segment>
    <movingRegion type="rect">
      <rectRegion x="49.92100" y="0.00000" w="20.33300" h="19.31000" t="0:00.000"/>
      <rectRegion x="49.92100" y="0.00000" w="20.33300" h="19.31000" t="0:16.600"/>
    </movingRegion>
  </segment>
  <appearance bgAlpha="0.25" bgColor="0" fgColor="16777215" textSize="3.911599999999999" effects="">
    
  </appearance>
  
  <action type="openUrl" trigger="click">
    <url target="current" value="https://www.youtube.com/watch?annotation_id=annotation_970789757&amp;ei=_3E9XKLTG8buD-_2oIgC&amp;feature=iv&amp;src_vid=ars5NVO1qHY&amp;v=ars5NVO1qHY#t=2m56s" link_class="1"/>
  </action>

</annotation></annotations></document>