<?xml version="1.0" encoding="UTF-8" ?><document><annotations itct="CAAQwOYBIhMI5OuZ5Irv3wIVwuSCCh3MOQa7KPgdMgJpdkiy48Ki6826-iQ">
<annotation id="annotation_65182" type="text" style="popup" log_data="a-v=JPTqbrRQsbI&amp;a-id=annotation_65182&amp;ei=jnM9XOTsM8LJiwTM85jYCw&amp;xble=1&amp;a-type=1" itct="CAEQs-UBGP___________wEiEwjk65nkiu_fAhXC5IIKHcw5Brso-B0yAml2SLLjwqLrzbr6JA">
  <TEXT>Thanks to an update, it&#39;s now named &#39;Source Engine 2006, 2007, 2009&#39;. Just find your game in one of those 3 menus and carry on as normal.</TEXT>
  <segment>
    <movingRegion type="rect">
      <rectRegion x="17.65600" y="83.33300" w="68.59400" h="11.66700" t="0:00:25.4"/>
      <rectRegion x="17.65600" y="83.33300" w="68.59400" h="11.66700" t="0:00:30.4"/>
    </movingRegion>
  </segment>
  <appearance bgAlpha="0.8" bgColor="16777215" fgColor="1710618" textSize="3.6107" effects="">
    
  </appearance>
  
</annotation><annotation author="3kliksphilip" id="annotation_809084" itct="CAIQs-UBGP___________wEiEwjk65nkiu_fAhXC5IIKHcw5Brso-B0yAml2SLLjwqLrzbr6JA" log_data="a-v=JPTqbrRQsbI&amp;a-id=annotation_809084&amp;ei=jnM9XOTsM8LJiwTM85jYCw&amp;xble=1&amp;a-type=2" style="speech" type="text"><TEXT>Day of Defeat Source</TEXT><segment><movingRegion type="anchored"><anchoredRegion d="0" h="11.111000061" sx="60.8330001831" sy="91.4810028076" t="0:00:50.0" w="30.625" x="50.4169998169" y="71.4810028076" /><anchoredRegion d="0" h="11.111000061" sx="60.8330001831" sy="91.4810028076" t="0:00:59.0" w="30.625" x="50.4169998169" y="71.4810028076" /></movingRegion></segment></annotation>
<annotation id="annotation_892328" type="text" style="popup" log_data="ei=jnM9XOTsM8LJiwTM85jYCw&amp;a-v=JPTqbrRQsbI&amp;link=http%3A%2F%2Fwww.youtube.com%2Fwatch%3Fv%3DHO1-RDcoe5U&amp;a-id=annotation_892328&amp;a-type=1&amp;xble=1&amp;l-class=1" itct="CAMQs-UBGP___________wEiEwjk65nkiu_fAhXC5IIKHcw5Brso-B0yAml2SLLjwqLrzbr6JA">
  <TEXT>THIS VIDEO IS OLD! There is a new, BETTER video out now, click on this to go to it.</TEXT>
  <segment>
    <movingRegion type="rect">
      <rectRegion x="14.84400" y="14.72200" w="69.68800" h="71.66700" t="0:00:00.0"/>
      <rectRegion x="14.84400" y="14.72200" w="69.68800" h="71.66700" t="0:00:10.0"/>
    </movingRegion>
  </segment>
  <appearance bgAlpha="0.800000011921" bgColor="13369344" fgColor="16777215" textSize="5.41605" effects="">
    
  </appearance>
  
  <action type="openUrl" trigger="click">
    <url target="current" value="https://www.youtube.com/watch?annotation_id=annotation_892328&amp;ei=jnM9XOTsM8LJiwTM85jYCw&amp;feature=iv&amp;src_vid=JPTqbrRQsbI&amp;v=HO1-RDcoe5U" link_class="1"/>
  </action>

</annotation></annotations></document>