<?xml version="1.0" encoding="UTF-8" ?><document><annotations itct="CAAQwOYBIhMIvuXr-9jt3wIVUBoDCh33wwL5KPgdMgJpdkjbhv7lssiZ9OkB">
<annotation id="annotation_203266" type="text" style="highlightText" logable="false" itct="">
  
  <segment spaceRelative="annotation_545891">
    <movingRegion type="rect">
      <rectRegion x="0.00000" y="29.72200" w="25.00000" h="5.55600" t="never"/>
      <rectRegion x="0.00000" y="29.72200" w="25.00000" h="5.55600" t="never"/>
    </movingRegion>
  </segment>
  <appearance bgAlpha="0" textSize="3.9116" highlightFontColor="15921906"/>
  <trigger>
    <condition ref="annotation_545891" state="rollOver"/>
  </trigger>
</annotation>

<annotation id="annotation_203803" type="text" style="highlightText" logable="false" itct="">
  <TEXT>Available Soon!</TEXT>
  <segment spaceRelative="annotation_749147">
    <movingRegion type="rect">
      <rectRegion x="1.71900" y="12.22200" w="25.00000" h="5.55600" t="never"/>
      <rectRegion x="1.71900" y="12.22200" w="25.00000" h="5.55600" t="never"/>
    </movingRegion>
  </segment>
  <appearance bgAlpha="0" textSize="3.9116" highlightFontColor="15921906"/>
  <trigger>
    <condition ref="annotation_749147" state="rollOver"/>
  </trigger>
</annotation>

<annotation id="annotation_423453" type="text" style="highlightText" logable="false" itct="">
  
  <segment spaceRelative="annotation_963696">
    <movingRegion type="rect">
      <rectRegion x="1.09400" y="12.50000" w="25.00000" h="5.55600" t="never"/>
      <rectRegion x="1.09400" y="12.50000" w="25.00000" h="5.55600" t="never"/>
    </movingRegion>
  </segment>
  <appearance bgAlpha="0" textSize="3.9116" highlightFontColor="15921906"/>
  <trigger>
    <condition ref="annotation_963696" state="rollOver"/>
  </trigger>
</annotation>

<annotation id="annotation_545891" type="highlight" log_data="link=http%3A%2F%2Fwww.youtube.com%2Fsubscription_center%3Fadd_user%3Dmcspotlights&amp;a-type=3&amp;ei=Grk8XL7wN9C0DPeHi8gP&amp;a-id=annotation_545891&amp;l-class=5&amp;xble=1&amp;a-v=6ehmQyy_g1s" itct="CAEQs-UBGP___________wEiEwi-5ev72O3fAhVQGgMKHffDAvko-B0yAml2SNuG_uWyyJn06QE">
  <segment>
    <movingRegion type="rect">
      <rectRegion x="31.09400" y="51.94400" w="37.81300" h="15.55600" t="0:00:50.9"/>
      <rectRegion x="31.09400" y="51.94400" w="37.81300" h="15.55600" t="0:01:02.5"/>
    </movingRegion>
  </segment>
  <appearance bgColor="16777215" highlightWidth="3" borderAlpha="0.25"/>
  
  <action type="openUrl" trigger="click">
    <url target="new" value="https://www.youtube.com/subscription_center?add_user=mcspotlights&amp;annotation_id=annotation_545891&amp;ei=Grk8XL7wN9C0DPeHi8gP&amp;feature=iv&amp;src_vid=6ehmQyy_g1s" link_class="5"/>
  </action>

</annotation>

<annotation id="annotation_749147" type="highlight" log_data="ei=Grk8XL7wN9C0DPeHi8gP&amp;a-id=annotation_749147&amp;xble=1&amp;a-type=3&amp;a-v=6ehmQyy_g1s" itct="CAIQs-UBGP___________wEiEwi-5ev72O3fAhVQGgMKHffDAvko-B0yAml2SNuG_uWyyJn06QE">
  <segment>
    <movingRegion type="rect">
      <rectRegion x="51.56300" y="3.05600" w="27.81300" h="32.22200" t="0:00:50.9"/>
      <rectRegion x="51.56300" y="3.05600" w="27.81300" h="32.22200" t="0:01:02.5"/>
    </movingRegion>
  </segment>
  <appearance bgColor="16777215" highlightWidth="3" borderAlpha="0.25"/>
  
</annotation>

<annotation id="annotation_963696" type="highlight" log_data="link=http%3A%2F%2Fwww.youtube.com%2Fwatch%3Fv%3DJ6oR3fdbbjY&amp;a-type=3&amp;ei=Grk8XL7wN9C0DPeHi8gP&amp;a-id=annotation_963696&amp;l-class=1&amp;xble=1&amp;a-v=6ehmQyy_g1s" itct="CAMQs-UBGP___________wEiEwi-5ev72O3fAhVQGgMKHffDAvko-B0yAml2SNuG_uWyyJn06QE">
  <segment>
    <movingRegion type="rect">
      <rectRegion x="22.96900" y="3.05600" w="27.65600" h="32.22200" t="0:00:50.9"/>
      <rectRegion x="22.96900" y="3.05600" w="27.65600" h="32.22200" t="0:01:02.5"/>
    </movingRegion>
  </segment>
  <appearance bgColor="16777215" highlightWidth="3" borderAlpha="0.25"/>
  
  <action type="openUrl" trigger="click">
    <url target="current" value="https://www.youtube.com/watch?annotation_id=annotation_963696&amp;ei=Grk8XL7wN9C0DPeHi8gP&amp;feature=iv&amp;src_vid=6ehmQyy_g1s&amp;v=J6oR3fdbbjY" link_class="1"/>
  </action>

</annotation>
</annotations></document>