<?xml version="1.0" encoding="UTF-8" ?><document><annotations itct="CAAQwOYBIhMIkr2Mj9rt3wIVg0AwCh0ItQr7KPgdMgJpdkjE452sg4SC5OcB">
<annotation id="annotation_341023" type="highlight" log_data="link=http%3A%2F%2Fwww.youtube.com%2Fsubscription_center%3Fadd_user%3Dmcspotlights&amp;xble=1&amp;ei=T7o8XNLZLIOBwQGI6qrYDw&amp;a-v=58gIIDWHccQ&amp;a-type=3&amp;a-id=annotation_341023&amp;l-class=5" itct="CAEQs-UBGP___________wEiEwiSvYyP2u3fAhWDQDAKHQi1Cvso-B0yAml2SMTjnayDhILk5wE">
  <segment>
    <movingRegion type="rect">
      <rectRegion x="29.84400" y="49.72200" w="40.31300" h="19.44400" t="0:01:05.5"/>
      <rectRegion x="29.84400" y="49.72200" w="40.31300" h="19.44400" t="0:01:05.5"/>
    </movingRegion>
  </segment>
  <appearance bgColor="16777215" highlightWidth="3" borderAlpha="0.25"/>
  
  <action type="openUrl" trigger="click">
    <url target="new" value="https://www.youtube.com/subscription_center?add_user=mcspotlights&amp;annotation_id=annotation_341023&amp;ei=T7o8XNLZLIOBwQGI6qrYDw&amp;feature=iv&amp;src_vid=58gIIDWHccQ" link_class="5"/>
  </action>

</annotation>

<annotation id="annotation_349861" type="text" style="highlightText" logable="false" itct="">
  
  <segment spaceRelative="annotation_893816">
    <movingRegion type="rect">
      <rectRegion x="1.25000" y="13.33300" w="25.00000" h="5.55600" t="never"/>
      <rectRegion x="1.25000" y="13.33300" w="25.00000" h="5.55600" t="never"/>
    </movingRegion>
  </segment>
  <appearance bgAlpha="0" textSize="3.9116" highlightFontColor="15921906"/>
  <trigger>
    <condition ref="annotation_893816" state="rollOver"/>
  </trigger>
</annotation>

<annotation id="annotation_503013" type="text" style="highlightText" logable="false" itct="">
  
  <segment spaceRelative="annotation_677403">
    <movingRegion type="rect">
      <rectRegion x="0.00000" y="29.72200" w="25.00000" h="5.55600" t="never"/>
      <rectRegion x="0.00000" y="29.72200" w="25.00000" h="5.55600" t="never"/>
    </movingRegion>
  </segment>
  <appearance bgAlpha="0" textSize="3.9116" highlightFontColor="15921906"/>
  <trigger>
    <condition ref="annotation_677403" state="rollOver"/>
  </trigger>
</annotation>

<annotation id="annotation_559495" type="text" style="highlightText" logable="false" itct="">
  
  <segment spaceRelative="annotation_341023">
    <movingRegion type="rect">
      <rectRegion x="0.00000" y="29.72200" w="25.00000" h="5.55600" t="never"/>
      <rectRegion x="0.00000" y="29.72200" w="25.00000" h="5.55600" t="never"/>
    </movingRegion>
  </segment>
  <appearance bgAlpha="0" textSize="3.9116" highlightFontColor="15921906"/>
  <trigger>
    <condition ref="annotation_341023" state="rollOver"/>
  </trigger>
</annotation>

<annotation id="annotation_676314" type="highlight" log_data="link=http%3A%2F%2Fwww.youtube.com%2Fwatch%3Fv%3DR-4ytK9Xt2M&amp;xble=1&amp;ei=T7o8XNLZLIOBwQGI6qrYDw&amp;a-v=58gIIDWHccQ&amp;a-type=3&amp;a-id=annotation_676314&amp;l-class=1" itct="CAIQs-UBGP___________wEiEwiSvYyP2u3fAhWDQDAKHQi1Cvso-B0yAml2SMTjnayDhILk5wE">
  <segment>
    <movingRegion type="rect">
      <rectRegion x="22.81300" y="3.05600" w="27.50000" h="32.22200" t="0:01:05.5"/>
      <rectRegion x="22.81300" y="3.05600" w="27.50000" h="32.22200" t="0:01:14.5"/>
    </movingRegion>
  </segment>
  <appearance bgColor="16777215" highlightWidth="3" borderAlpha="0.25"/>
  
  <action type="openUrl" trigger="click">
    <url target="current" value="https://www.youtube.com/watch?annotation_id=annotation_676314&amp;ei=T7o8XNLZLIOBwQGI6qrYDw&amp;feature=iv&amp;src_vid=58gIIDWHccQ&amp;v=R-4ytK9Xt2M" link_class="1"/>
  </action>

</annotation>

<annotation id="annotation_677403" type="highlight" log_data="link=http%3A%2F%2Fwww.youtube.com%2Fsubscription_center%3Fadd_user%3Dmcspotlights&amp;xble=1&amp;ei=T7o8XNLZLIOBwQGI6qrYDw&amp;a-v=58gIIDWHccQ&amp;a-type=3&amp;a-id=annotation_677403&amp;l-class=5" itct="CAMQs-UBGP___________wEiEwiSvYyP2u3fAhWDQDAKHQi1Cvso-B0yAml2SMTjnayDhILk5wE">
  <segment>
    <movingRegion type="rect">
      <rectRegion x="29.68800" y="49.44400" w="41.09400" h="20.00000" t="0:01:05.5"/>
      <rectRegion x="29.68800" y="49.44400" w="41.09400" h="20.00000" t="0:01:14.5"/>
    </movingRegion>
  </segment>
  <appearance bgColor="16777215" highlightWidth="3" borderAlpha="0.25"/>
  
  <action type="openUrl" trigger="click">
    <url target="new" value="https://www.youtube.com/subscription_center?add_user=mcspotlights&amp;annotation_id=annotation_677403&amp;ei=T7o8XNLZLIOBwQGI6qrYDw&amp;feature=iv&amp;src_vid=58gIIDWHccQ" link_class="5"/>
  </action>

</annotation>

<annotation id="annotation_857920" type="text" style="highlightText" logable="false" itct="">
  
  <segment spaceRelative="annotation_676314">
    <movingRegion type="rect">
      <rectRegion x="0.00000" y="29.72200" w="25.00000" h="5.55600" t="never"/>
      <rectRegion x="0.00000" y="29.72200" w="25.00000" h="5.55600" t="never"/>
    </movingRegion>
  </segment>
  <appearance bgAlpha="0" textSize="3.9116" highlightFontColor="15921906"/>
  <trigger>
    <condition ref="annotation_676314" state="rollOver"/>
  </trigger>
</annotation>

<annotation id="annotation_893816" type="highlight" log_data="link=http%3A%2F%2Fwww.youtube.com%2Fwatch%3Fv%3Dd22hh9vwuQE&amp;xble=1&amp;ei=T7o8XNLZLIOBwQGI6qrYDw&amp;a-v=58gIIDWHccQ&amp;a-type=3&amp;a-id=annotation_893816&amp;l-class=1" itct="CAQQs-UBGP___________wEiEwiSvYyP2u3fAhWDQDAKHQi1Cvso-B0yAml2SMTjnayDhILk5wE">
  <segment>
    <movingRegion type="rect">
      <rectRegion x="51.87500" y="3.33300" w="27.50000" h="32.22200" t="0:01:05.5"/>
      <rectRegion x="51.87500" y="3.33300" w="27.50000" h="32.22200" t="0:01:14.5"/>
    </movingRegion>
  </segment>
  <appearance bgColor="16777215" highlightWidth="3" borderAlpha="0.25"/>
  
  <action type="openUrl" trigger="click">
    <url target="current" value="https://www.youtube.com/watch?annotation_id=annotation_893816&amp;ei=T7o8XNLZLIOBwQGI6qrYDw&amp;feature=iv&amp;src_vid=58gIIDWHccQ&amp;v=d22hh9vwuQE" link_class="1"/>
  </action>

</annotation>
</annotations></document>