<?xml version="1.0" encoding="UTF-8" ?><document><annotations itct="CAAQwOYBIhMI25vJz_7u3wIVjnyDCh1M3QKdKPgdMgJpdkizxtq-2fnDtNwB">
<annotation id="annotation_1242564529" type="text" style="popup" log_data="a-v=3GkPzZfWozM&amp;xble=1&amp;l-class=1&amp;a-id=annotation_1242564529&amp;ei=zmY9XNv8FY75jQTMuovoCQ&amp;a-type=1&amp;link=http%3A%2F%2Fwww.youtube.com%2Fwatch%3Fv%3DwFW3xc4UJDM%26list%3DPLFB5709A13973AE0D" itct="CAEQs-UBGP___________wEiEwjbm8nP_u7fAhWOfIMKHUzdAp0o-B0yAml2SLPG2r7Z-cO03AE">
  <TEXT>How to be extremely agro demoman</TEXT>
  <segment>
    <movingRegion type="rect">
      <rectRegion x="10.77700" y="55.49300" w="81.81500" h="12.54900" t="0:41.019"/>
      <rectRegion x="10.77700" y="55.49300" w="81.81500" h="12.54900" t="0:53.900"/>
    </movingRegion>
  </segment>
  <appearance bgAlpha="0.600000023842" bgColor="10277594" fgColor="0" textSize="8.424966666666666" effects="">
    
  </appearance>
  
  <action type="openUrl" trigger="click">
    <url target="current" value="https://www.youtube.com/watch?annotation_id=annotation_1242564529&amp;ei=zmY9XNv8FY75jQTMuovoCQ&amp;feature=iv&amp;list=PLFB5709A13973AE0D&amp;src_vid=3GkPzZfWozM&amp;v=wFW3xc4UJDM" link_class="1"/>
  </action>

</annotation>
<annotation id="annotation_1371555589" type="text" style="popup" log_data="a-v=3GkPzZfWozM&amp;xble=1&amp;l-class=1&amp;a-id=annotation_1371555589&amp;ei=zmY9XNv8FY75jQTMuovoCQ&amp;a-type=1&amp;link=http%3A%2F%2Fwww.youtube.com%2Fwatch%3Fv%3D4X3n_X1132g%26list%3DPLA3B6E9FC1447BDDD" itct="CAIQs-UBGP___________wEiEwjbm8nP_u7fAhWOfIMKHUzdAp0o-B0yAml2SLPG2r7Z-cO03AE">
  <TEXT>#176 Freeman (demoman)</TEXT>
  <segment>
    <movingRegion type="rect">
      <rectRegion x="0.00000" y="0.00000" w="36.33100" h="24.09900" t="0:41.019"/>
      <rectRegion x="0.00000" y="0.00000" w="36.33100" h="24.09900" t="0:53.900"/>
    </movingRegion>
  </segment>
  <appearance bgAlpha="0.600000023842" bgColor="16636470" fgColor="0" textSize="8.424966666666666" effects="">
    
  </appearance>
  
  <action type="openUrl" trigger="click">
    <url target="current" value="https://www.youtube.com/watch?annotation_id=annotation_1371555589&amp;ei=zmY9XNv8FY75jQTMuovoCQ&amp;feature=iv&amp;list=PLA3B6E9FC1447BDDD&amp;src_vid=3GkPzZfWozM&amp;v=4X3n_X1132g" link_class="1"/>
  </action>

</annotation>
<annotation id="annotation_3301130849" type="text" style="popup" log_data="a-v=3GkPzZfWozM&amp;xble=1&amp;l-class=1&amp;a-id=annotation_3301130849&amp;ei=zmY9XNv8FY75jQTMuovoCQ&amp;a-type=1&amp;link=http%3A%2F%2Fwww.youtube.com%2Fwatch%3Fv%3DUnuOIuUOTEI%26list%3DPLFB5709A13973AE0D" itct="CAMQs-UBGP___________wEiEwjbm8nP_u7fAhWOfIMKHUzdAp0o-B0yAml2SLPG2r7Z-cO03AE">
  <TEXT>How to trade roamers</TEXT>
  <segment>
    <movingRegion type="rect">
      <rectRegion x="24.08900" y="68.73200" w="50.91100" h="13.67600" t="0:41.019"/>
      <rectRegion x="24.08900" y="68.73200" w="50.91100" h="13.67600" t="0:53.900"/>
    </movingRegion>
  </segment>
  <appearance bgAlpha="0.600000023842" bgColor="10415454" fgColor="0" textSize="8.424966666666666" effects="">
    
  </appearance>
  
  <action type="openUrl" trigger="click">
    <url target="current" value="https://www.youtube.com/watch?annotation_id=annotation_3301130849&amp;ei=zmY9XNv8FY75jQTMuovoCQ&amp;feature=iv&amp;list=PLFB5709A13973AE0D&amp;src_vid=3GkPzZfWozM&amp;v=UnuOIuUOTEI" link_class="1"/>
  </action>

</annotation>
<annotation id="annotation_674801051" type="text" style="popup" log_data="a-v=3GkPzZfWozM&amp;xble=1&amp;l-class=1&amp;a-id=annotation_674801051&amp;ei=zmY9XNv8FY75jQTMuovoCQ&amp;a-type=1&amp;link=http%3A%2F%2Fwww.youtube.com%2Fwatch%3Fv%3Do-GjL7kUBi0%26list%3DPLFB5709A13973AE0D" itct="CAQQs-UBGP___________wEiEwjbm8nP_u7fAhWOfIMKHUzdAp0o-B0yAml2SLPG2r7Z-cO03AE">
  <TEXT>How to tele camp with pyro</TEXT>
  <segment>
    <movingRegion type="rect">
      <rectRegion x="17.90800" y="82.81700" w="62.33000" h="13.67600" t="0:41.019"/>
      <rectRegion x="17.90800" y="82.81700" w="62.33000" h="13.67600" t="0:53.900"/>
    </movingRegion>
  </segment>
  <appearance bgAlpha="0.600000023842" bgColor="14048063" fgColor="0" textSize="8.424966666666666" effects="">
    
  </appearance>
  
  <action type="openUrl" trigger="click">
    <url target="current" value="https://www.youtube.com/watch?annotation_id=annotation_674801051&amp;ei=zmY9XNv8FY75jQTMuovoCQ&amp;feature=iv&amp;list=PLFB5709A13973AE0D&amp;src_vid=3GkPzZfWozM&amp;v=o-GjL7kUBi0" link_class="1"/>
  </action>

</annotation>
<annotation id="annotation_825647577" type="text" style="popup" log_data="a-v=3GkPzZfWozM&amp;xble=1&amp;l-class=1&amp;a-id=annotation_825647577&amp;ei=zmY9XNv8FY75jQTMuovoCQ&amp;a-type=1&amp;link=http%3A%2F%2Fwww.youtube.com%2Fwatch%3Fv%3DVzRh0ZEw4SI%26list%3DPLA3B6E9FC1447BDDD" itct="CAUQs-UBGP___________wEiEwjbm8nP_u7fAhWOfIMKHUzdAp0o-B0yAml2SLPG2r7Z-cO03AE">
  <TEXT>#178 plex (scout)</TEXT>
  <segment>
    <movingRegion type="rect">
      <rectRegion x="63.33600" y="0.00000" w="36.66400" h="24.38000" t="0:41.019"/>
      <rectRegion x="63.33600" y="0.00000" w="36.66400" h="24.38000" t="0:53.900"/>
    </movingRegion>
  </segment>
  <appearance bgAlpha="0.600000023842" bgColor="16564776" fgColor="0" textSize="8.424966666666666" effects="">
    
  </appearance>
  
  <action type="openUrl" trigger="click">
    <url target="current" value="https://www.youtube.com/watch?annotation_id=annotation_825647577&amp;ei=zmY9XNv8FY75jQTMuovoCQ&amp;feature=iv&amp;list=PLA3B6E9FC1447BDDD&amp;src_vid=3GkPzZfWozM&amp;v=VzRh0ZEw4SI" link_class="1"/>
  </action>

</annotation></annotations></document>